MANIFEST.in
README.md
setup.py
graphkit/__init__.py
graphkit/base.py
graphkit/functional.py
graphkit/modifiers.py
graphkit/network.py
graphkit.egg-info/PKG-INFO
graphkit.egg-info/SOURCES.txt
graphkit.egg-info/dependency_links.txt
graphkit.egg-info/requires.txt
graphkit.egg-info/top_level.txt
test/test_graphkit.py